numbers_almost_equal/LICENSE
numbers_almost_equal/README.MD
numbers_almost_equal/__init__.py
numbers_almost_equal/requirements.txt
numbers_almost_equal/thirdparty.json
numbers_almost_equal-0.11.dist-info/LICENSE.rst
numbers_almost_equal-0.11.dist-info/METADATA
numbers_almost_equal-0.11.dist-info/WHEEL
numbers_almost_equal-0.11.dist-info/top_level.txt
numbers_almost_equal-0.11.dist-info/RECORD
